panlit
