Metadata-Version: 2.4
Name: panlit
Version: 0.1.2
Summary: A Python package that depends on Streamlit
Author: Pan Lancer
License-File: LICENSE
Requires-Dist: streamlit>=1.0.0
Dynamic: author
Dynamic: license-file
Dynamic: requires-dist
Dynamic: summary
